[
  {
    "category": "vehicle",
    "key": "responder",
    "name": "Dune Responder 3e",
    "bmat": 150,
    "emat": 0,
    "hemat": 0,
    "rmat": 0,
    "requireTech": true,
    "ammo": []
  },
  {
    "category": "vehicle",
    "key": "highlander",
    "name": "O'Brien v.121 Highlander",
    "bmat": 0,
    "emat": 0,
    "hemat": 0,
    "rmat": 40,
    "requireTech": true,
    "ammo": []
  },
  {
    "category": "vehicle",
    "key": "freeman",
    "name": "O'Brien V.101 Freeman",
    "bmat": 0,
    "emat": 0,
    "hemat": 0,
    "rmat": 60,
    "requireTech": true,
    "ammo": []
  },
  {
    "category": "vehicle",
    "key": "obrien",
    "name": "O'Brien v.110",
    "bmat": 0,
    "emat": 0,
    "hemat": 0,
    "rmat": 45,
    "requireTech": true,
    "ammo": []
  },
  {
    "category": "vehicle",
    "key": "juggernaut",
    "name": "Flood Juggernaut Mk.VII",
    "bmat": 0,
    "emat": 0,
    "hemat": 0,
    "rmat": 490,
    "requireTech": true,
    "ammo": []
  },
  {
    "category": "vehicle",
    "key": "ascension",
    "name": "Flood Ascension Mk.V",
    "bmat": 0,
    "emat": 0,
    "hemat": 0,
    "rmat": 470,
    "requireTech": true,
    "ammo": []
  },
  {
    "category": "vehicle",
    "key": "flood",
    "name": "Flood Mk.1",
    "bmat": 0,
    "emat": 0,
    "hemat": 0,
    "rmat": 400,
    "requireTech": true,
    "ammo": []
  },
  {
    "category": "vehicle",
    "key": "caravaner",
    "name": "Dunne Caravaner 2f",
    "bmat": 100,
    "emat": 0,
    "hemat": 0,
    "rmat": 0,
    "requireTech": true,
    "ammo": []
  },
  {
    "category": "vehicle",
    "key": "noble",
    "name": "Noble Widow MK.XIV",
    "bmat": 0,
    "emat": 0,
    "hemat": 0,
    "rmat": 160,
    "requireTech": true,
    "ammo": []
  },
  {
    "category": "vehicle",
    "key": "collins",
    "name": "Collins Cannon 68mm",
    "bmat": 0,
    "emat": 0,
    "hemat": 0,
    "rmat": 30,
    "requireTech": true,
    "ammo": []
  },
  {
    "category": "vehicle",
    "key": "wolfhound",
    "name": "Balfour Wolfhound 40mm",
    "bmat": 0,
    "emat": 0,
    "hemat": 0,
    "rmat": 30,
    "requireTech": true,
    "ammo": []
  },
  {
    "category": "vehicle",
    "key": "swallowtail",
    "name": "Swallowtail 988/145-2",
    "bmat": 0,
    "emat": 0,
    "hemat": 0,
    "rmat": 25,
    "requireTech": true,
    "ammo": []
  },
  {
    "category": "vehicle",
    "key": "falconer",
    "name": "Balfour Falconer 250mm",
    "bmat": 0,
    "emat": 0,
    "hemat": 0,
    "rmat": 35,
    "requireTech": true,
    "ammo": []
  },
  {
    "category": "vehicle",
    "key": "flatbed",
    "name": "BMS - Packmule Flatbed",
    "bmat": 0,
    "emat": 0,
    "hemat": 0,
    "rmat": 30,
    "requireTech": false,
    "ammo": []
  },
  {
    "category": "vehicle",
    "key": "blinder",
    "name": "Niska Mk.2 Blinder",
    "bmat": 0,
    "emat": 0,
    "hemat": 0,
    "rmat": 85,
    "requireTech": true,
    "ammo": []
  },
  {
    "category": "vehicle",
    "key": "niska",
    "name": "Niska Mk.1 Gun Motor Carriage",
    "bmat": 0,
    "emat": 0,
    "hemat": 0,
    "rmat": 60,
    "requireTech": true,
    "ammo": []
  },
  {
    "category": "vehicle",
    "key": "scraphauler",
    "name": "BMS - Scrap Hauler",
    "bmat": 0,
    "emat": 0,
    "hemat": 0,
    "rmat": 120,
    "requireTech": true,
    "ammo": []
  },
  {
    "category": "vehicle",
    "key": "mulloy",
    "name": "Mulloy LPC",
    "bmat": 0,
    "emat": 0,
    "hemat": 0,
    "rmat": 400,
    "requireTech": true,
    "ammo": []
  },
  {
    "category": "vehicle",
    "key": "caine",
    "name": "Devitt-Caine MK-IV MMR",
    "bmat": 0,
    "emat": 0,
    "hemat": 0,
    "rmat": 150,
    "requireTech": true,
    "ammo": []
  },
  {
    "category": "vehicle",
    "key": "ironhide",
    "name": "Devitt Ironhide Mk.IV",
    "bmat": 0,
    "emat": 0,
    "hemat": 0,
    "rmat": 160,
    "requireTech": true,
    "ammo": []
  },
  {
    "category": "vehicle",
    "key": "devitt",
    "name": "Devitt Mk.II",
    "bmat": 0,
    "emat": 0,
    "hemat": 0,
    "rmat": 140,
    "requireTech": true,
    "ammo": []
  },
  {
    "category": "vehicle",
    "key": "silverhand",
    "name": "Silverhand - Mk.IV",
    "bmat": 0,
    "emat": 0,
    "hemat": 0,
    "rmat": 170,
    "requireTech": true,
    "ammo": []
  },
  {
    "category": "vehicle",
    "key": "kivela",
    "name": "Kivela Power Wheel 80-1",
    "bmat": 85,
    "emat": 0,
    "hemat": 0,
    "rmat": 0,
    "requireTech": true,
    "ammo": []
  },
  {
    "category": "vehicle",
    "key": "fuelrunner",
    "name": "Dunne Fuelrunner 2d",
    "bmat": 100,
    "emat": 0,
    "hemat": 0,
    "rmat": 0,
    "requireTech": false,
    "ammo": []
  },
  {
    "category": "vehicle",
    "key": "transport",
    "name": "Dunne Transport",
    "bmat": 100,
    "emat": 0,
    "hemat": 0,
    "rmat": 0,
    "requireTech": false,
    "ammo": []
  },
  {
    "category": "vehicle",
    "key": "landrunner",
    "name": "Dunne Landrunner 12c",
    "bmat": 120,
    "emat": 0,
    "hemat": 0,
    "rmat": 0,
    "requireTech": true,
    "ammo": []
  },
  {
    "category": "vehicle",
    "key": "loadlugger",
    "name": "Dunne Loadlugger 3c",
    "bmat": 120,
    "emat": 0,
    "hemat": 0,
    "rmat": 0,
    "requireTech": true,
    "ammo": []
  },
  {
    "category": "vehicle",
    "key": "leatherback",
    "name": "Dunne Leatherback 2a",
    "bmat": 145,
    "emat": 0,
    "hemat": 0,
    "rmat": 0,
    "requireTech": true,
    "ammo": []
  },
  {
    "category": "vehicle",
    "key": "drummond",
    "name": "Drummond 100a",
    "bmat": 0,
    "emat": 0,
    "hemat": 0,
    "rmat": 10,
    "requireTech": true,
    "ammo": []
  },
  {
    "category": "vehicle",
    "key": "kingspire",
    "name": "King Spire MK-I",
    "bmat": 0,
    "emat": 0,
    "hemat": 0,
    "rmat": 80,
    "requireTech": true,
    "ammo": []
  },
  {
    "category": "vehicle",
    "key": "spitfire",
    "name": "Drummond Spitfire 100d",
    "bmat": 0,
    "emat": 0,
    "hemat": 0,
    "rmat": 15,
    "requireTech": true,
    "ammo": []
  },
  {
    "category": "vehicle",
    "key": "loscann",
    "name": "Drummond Loscann 55c",
    "bmat": 0,
    "emat": 0,
    "hemat": 0,
    "rmat": 10,
    "requireTech": true,
    "ammo": []
  }
]